slmpclient/client.py
slmpclient/slmp_controller.py
slmpclient/__init__.py
slmpclient/const.py
slmpclient/util.py
slmpclient/clib/slmp_c.cpython-38-i386-linux-gnu.so
slmpclient-2.0.2.dist-info/METADATA
slmpclient-2.0.2.dist-info/top_level.txt
slmpclient-2.0.2.dist-info/WHEEL
slmpclient-2.0.2.dist-info/RECORD
