Metadata-Version: 2.1
Name: slmpclient
Version: 2.0.2
Summary: UNKNOWN
Home-page: UNKNOWN
Author: Roland Zitny
License: UNKNOWN
Platform: UNKNOWN
